zarcrender/__init__.py
zarcrender/config.py
zarcrender/constant.py
zarcrender/helper.py
zarcrender/json.py
zarcrender/parser.py
zarcrender/query.py
zarcrender-1.0.1.dist-info/LICENSE
zarcrender-1.0.1.dist-info/METADATA
zarcrender-1.0.1.dist-info/WHEEL
zarcrender-1.0.1.dist-info/top_level.txt
zarcrender-1.0.1.dist-info/RECORD
